buckeyelabs/__init__.py
buckeyelabs/__main__.py
buckeyelabs/settings.py
buckeyelabs/types.py
buckeyelabs/version.py
buckeyelabs/agents/__init__.py
buckeyelabs/agents/base.py
buckeyelabs/agents/claude.py
buckeyelabs/agents/langchain.py
buckeyelabs/agents/openai.py
buckeyelabs/agents/openai_chat_generic.py
buckeyelabs/agents/misc/__init__.py
buckeyelabs/agents/misc/response_agent.py
buckeyelabs/cli/__init__.py
buckeyelabs/cli/__main__.py
buckeyelabs/cli/analyze.py
buckeyelabs/cli/build.py
buckeyelabs/cli/clone.py
buckeyelabs/cli/debug.py
buckeyelabs/cli/dev.py
buckeyelabs/cli/eval.py
buckeyelabs/cli/hf.py
buckeyelabs/cli/init.py
buckeyelabs/cli/list_func.py
buckeyelabs/cli/pull.py
buckeyelabs/cli/push.py
buckeyelabs/cli/remove.py
buckeyelabs/cli/rl/README.md
buckeyelabs/cli/rl/__init__.py
buckeyelabs/cli/rl/init.py
buckeyelabs/cli/rl/pod.py
buckeyelabs/cli/rl/ssh.py
buckeyelabs/cli/rl/train.py
buckeyelabs/cli/rl/utils.py
buckeyelabs/cli/utils/__init__.py
buckeyelabs/cli/utils/cursor.py
buckeyelabs/cli/utils/docker.py
buckeyelabs/cli/utils/environment.py
buckeyelabs/cli/utils/interactive.py
buckeyelabs/cli/utils/logging.py
buckeyelabs/cli/utils/metadata.py
buckeyelabs/cli/utils/registry.py
buckeyelabs/cli/utils/remote_runner.py
buckeyelabs/cli/utils/runner.py
buckeyelabs/cli/utils/server.py
buckeyelabs/clients/README.md
buckeyelabs/clients/__init__.py
buckeyelabs/clients/base.py
buckeyelabs/clients/fastmcp.py
buckeyelabs/clients/mcp_use.py
buckeyelabs/clients/utils/__init__.py
buckeyelabs/clients/utils/retry_transport.py
buckeyelabs/datasets/__init__.py
buckeyelabs/datasets/task.py
buckeyelabs/datasets/utils.py
buckeyelabs/datasets/execution/__init__.py
buckeyelabs/datasets/execution/parallel.py
buckeyelabs/datasets/execution/runner.py
buckeyelabs/misc/__init__.py
buckeyelabs/misc/claude_plays_pokemon.py
buckeyelabs/otel/__init__.py
buckeyelabs/otel/collector.py
buckeyelabs/otel/config.py
buckeyelabs/otel/context.py
buckeyelabs/otel/exporters.py
buckeye_python-0.1.0.dist-info/METADATA
buckeye_python-0.1.0.dist-info/WHEEL
buckeye_python-0.1.0.dist-info/entry_points.txt
buckeye_python-0.1.0.dist-info/licenses/LICENSE
buckeye_python-0.1.0.dist-info/RECORD
