Metadata-Version: 2.4
Name: buckeye-python
Version: 0.1.0
Summary: Buckeye platform for sdk.
Project-URL: Homepage, https://github.com/buckeye/buckeye-python
Project-URL: Bug Tracker, https://github.com/buckeye/buckeye-python/issues
Project-URL: Documentation, https://doc.buckeye.ai
Author-email: Jahid Hasan <you@example.com>
License: MIT License
License-File: LICENSE
Classifier: Development Status :: 4 - Beta
Classifier: Intended Audience :: Developers
Classifier: Programming Language :: Python :: 3
Classifier: Programming Language :: Python :: 3.11
Classifier: Programming Language :: Python :: 3.12
Classifier: Programming Language :: Python :: 3.13
Requires-Python: <3.14,>=3.11
Requires-Dist: fastmcp>=2.12.0
Requires-Dist: httpx<1,>=0.23.0
Requires-Dist: mcp>=1.13.1
Requires-Dist: opentelemetry-api>=1.34.1
Requires-Dist: opentelemetry-exporter-otlp-proto-http>=1.34.1
Requires-Dist: opentelemetry-instrumentation-mcp>=0.44.1
Requires-Dist: opentelemetry-sdk>=1.34.1
Requires-Dist: pathspec>=0.12.1
Requires-Dist: prompt-toolkit==3.0.51
Requires-Dist: pydantic-settings<3,>=2
Requires-Dist: pydantic<3,>=2
Requires-Dist: python-dotenv>=1.0.0
Requires-Dist: questionary==2.1.0
Requires-Dist: rich>=13.0.0
Requires-Dist: toml>=0.10.2
Requires-Dist: typer>=0.9.0
Requires-Dist: verifiers>=0.1.3
Requires-Dist: watchfiles>=0.21.0
Requires-Dist: wrapt>=1.14.0
Provides-Extra: agent
Requires-Dist: anthropic; extra == 'agent'
Requires-Dist: datasets>=4.0.0; extra == 'agent'
Requires-Dist: dotenv>=0.9.9; extra == 'agent'
Requires-Dist: ipykernel; extra == 'agent'
Requires-Dist: ipython<9; extra == 'agent'
Requires-Dist: jupyter-client; extra == 'agent'
Requires-Dist: jupyter-core; extra == 'agent'
Requires-Dist: langchain; extra == 'agent'
Requires-Dist: langchain-anthropic; extra == 'agent'
Requires-Dist: langchain-openai; extra == 'agent'
Requires-Dist: mcp-use>=1.3.10; extra == 'agent'
Requires-Dist: numpy>=1.24.0; extra == 'agent'
Requires-Dist: openai; extra == 'agent'
Provides-Extra: agents
Requires-Dist: anthropic; extra == 'agents'
Requires-Dist: datasets>=4.0.0; extra == 'agents'
Requires-Dist: dotenv>=0.9.9; extra == 'agents'
Requires-Dist: ipykernel; extra == 'agents'
Requires-Dist: ipython<9; extra == 'agents'
Requires-Dist: jupyter-client; extra == 'agents'
Requires-Dist: jupyter-core; extra == 'agents'
Requires-Dist: langchain; extra == 'agents'
Requires-Dist: langchain-anthropic; extra == 'agents'
Requires-Dist: langchain-openai; extra == 'agents'
Requires-Dist: mcp-use>=1.3.10; extra == 'agents'
Requires-Dist: numpy>=1.24.0; extra == 'agents'
Requires-Dist: openai; extra == 'agents'
Provides-Extra: dev
Requires-Dist: aiodocker>=0.24.0; extra == 'dev'
Requires-Dist: anthropic; extra == 'dev'
Requires-Dist: datasets>=4.0.0; extra == 'dev'
Requires-Dist: dotenv>=0.9.9; extra == 'dev'
Requires-Dist: inspect-ai>=0.3.80; extra == 'dev'
Requires-Dist: ipykernel; extra == 'dev'
Requires-Dist: ipython<9; extra == 'dev'
Requires-Dist: jupyter-client; extra == 'dev'
Requires-Dist: jupyter-core; extra == 'dev'
Requires-Dist: langchain; extra == 'dev'
Requires-Dist: langchain-anthropic; extra == 'dev'
Requires-Dist: langchain-openai; extra == 'dev'
Requires-Dist: mcp-use>=1.3.10; extra == 'dev'
Requires-Dist: numpy>=1.24.0; extra == 'dev'
Requires-Dist: openai; extra == 'dev'
Requires-Dist: pillow>=11.1.0; extra == 'dev'
Requires-Dist: playwright; extra == 'dev'
Requires-Dist: pyautogui>=0.9.54; extra == 'dev'
Requires-Dist: pyright==1.1.401; extra == 'dev'
Requires-Dist: pytest-asyncio; extra == 'dev'
Requires-Dist: pytest-cov; extra == 'dev'
Requires-Dist: pytest-mock; extra == 'dev'
Requires-Dist: pytest<9,>=8.1.1; extra == 'dev'
Requires-Dist: ruff>=0.11.8; extra == 'dev'
Requires-Dist: setuptools; extra == 'dev'
Requires-Dist: textdistance<5,>=4.5.0; extra == 'dev'
